{
	"version": "2.0",
	"name": "161111_230104_1",
	"description": "",
	"points": 1074063,
	"projection": "",
	"hierarchy": {
		"firstChunkSize": 968, 
		"stepSize": 4, 
		"depth": 12
	},
	"offset": [-768.60300000000007, -1227.8020000000001, -40.718000000000004],
	"scale": [0.001, 0.001, 0.001],
	"spacing": 18.042523437500002,
	"boundingBox": {
		"min": [-768.60300000000007, -1227.8020000000001, -40.718000000000004], 
		"max": [1540.8400000000001, 1081.6410000000001, 2268.7250000000004]
	},
	"encoding": "default",
	"attributes": [
		{
			"name": "position",
			"description": "",
			"size": 12,
			"numElements": 3,
			"elementSize": 4,
			"type": "int32",
			"min": [-768.60300000000007, -1227.8020000000001, -40.718000000000004],
			"max": [164.28999999999999, 1081.6410000000001, 76.475000000000009],
			"scale": [1, 1, 1],
			"offset": [0, 0, 0]
		},{
			"name": "intensity",
			"description": "",
			"size": 2,
			"numElements": 1,
			"elementSize": 2,
			"type": "uint16",
			"min": [0],
			"max": [0],
			"scale": [1],
			"offset": [0]
		},{
			"name": "return number",
			"description": "",
			"size": 1,
			"numElements": 1,
			"elementSize": 1,
			"type": "uint8",
			"min": [1],
			"max": [1],
			"scale": [1],
			"offset": [0]
		},{
			"name": "number of returns",
			"description": "",
			"size": 1,
			"numElements": 1,
			"elementSize": 1,
			"type": "uint8",
			"min": [1],
			"max": [1],
			"scale": [1],
			"offset": [0]
		},{
			"name": "classification",
			"description": "",
			"size": 1,
			"numElements": 1,
			"elementSize": 1,
			"type": "uint8",
			"histogram": [1074063, 0, 0, 0, 0, 0, 0, 0, 0, 0, 0, 0, 0, 0, 0, 0, 0, 0, 0, 0, 0, 0, 0, 0, 0, 0, 0, 0, 0, 0, 0, 0, 0, 0, 0, 0, 0, 0, 0, 0, 0, 0, 0, 0, 0, 0, 0, 0, 0, 0, 0, 0, 0, 0, 0, 0, 0, 0, 0, 0, 0, 0, 0, 0, 0, 0, 0, 0, 0, 0, 0, 0, 0, 0, 0, 0, 0, 0, 0, 0, 0, 0, 0, 0, 0, 0, 0, 0, 0, 0, 0, 0, 0, 0, 0, 0, 0, 0, 0, 0, 0, 0, 0, 0, 0, 0, 0, 0, 0, 0, 0, 0, 0, 0, 0, 0, 0, 0, 0, 0, 0, 0, 0, 0, 0, 0, 0, 0, 0, 0, 0, 0, 0, 0, 0, 0, 0, 0, 0, 0, 0, 0, 0, 0, 0, 0, 0, 0, 0, 0, 0, 0, 0, 0, 0, 0, 0, 0, 0, 0, 0, 0, 0, 0, 0, 0, 0, 0, 0, 0, 0, 0, 0, 0, 0, 0, 0, 0, 0, 0, 0, 0, 0, 0, 0, 0, 0, 0, 0, 0, 0, 0, 0, 0, 0, 0, 0, 0, 0, 0, 0, 0, 0, 0, 0, 0, 0, 0, 0, 0, 0, 0, 0, 0, 0, 0, 0, 0, 0, 0, 0, 0, 0, 0, 0, 0, 0, 0, 0, 0, 0, 0, 0, 0, 0, 0, 0, 0, 0, 0, 0, 0, 0, 0, 0, 0, 0, 0, 0, 0, 0, 0, 0, 0, 0, 0], 
			"min": [0],
			"max": [0],
			"scale": [1],
			"offset": [0]
		},{
			"name": "scan angle rank",
			"description": "",
			"size": 1,
			"numElements": 1,
			"elementSize": 1,
			"type": "uint8",
			"min": [0],
			"max": [0],
			"scale": [1],
			"offset": [0]
		},{
			"name": "user data",
			"description": "",
			"size": 1,
			"numElements": 1,
			"elementSize": 1,
			"type": "uint8",
			"min": [0],
			"max": [0],
			"scale": [1],
			"offset": [0]
		},{
			"name": "point source id",
			"description": "",
			"size": 2,
			"numElements": 1,
			"elementSize": 2,
			"type": "uint16",
			"min": [0],
			"max": [0],
			"scale": [1],
			"offset": [0]
		},{
			"name": "range",
			"description": "",
			"size": 4,
			"numElements": 1,
			"elementSize": 4,
			"type": "int32",
			"min": [327],
			"max": [1266478],
			"scale": [0.001],
			"offset": [0]
		},{
			"name": "theta",
			"description": "",
			"size": 4,
			"numElements": 1,
			"elementSize": 4,
			"type": "int32",
			"min": [377420],
			"max": [1300871],
			"scale": [0.0001],
			"offset": [0]
		},{
			"name": "phi",
			"description": "",
			"size": 4,
			"numElements": 1,
			"elementSize": 4,
			"type": "int32",
			"min": [837334],
			"max": [2940945],
			"scale": [0.0001],
			"offset": [0]
		},{
			"name": "reflectance",
			"description": "",
			"size": 4,
			"numElements": 1,
			"elementSize": 4,
			"type": "int32",
			"min": [-42280],
			"max": [23551],
			"scale": [0.001],
			"offset": [0]
		},{
			"name": "amplitude",
			"description": "",
			"size": 4,
			"numElements": 1,
			"elementSize": 4,
			"type": "int32",
			"min": [110],
			"max": [6222],
			"scale": [0.01],
			"offset": [0]
		},{
			"name": "deviation",
			"description": "",
			"size": 2,
			"numElements": 1,
			"elementSize": 2,
			"type": "int16",
			"min": [-1],
			"max": [706],
			"scale": [1],
			"offset": [0]
		},{
			"name": "echo",
			"description": "",
			"size": 1,
			"numElements": 1,
			"elementSize": 1,
			"type": "uint8",
			"min": [0],
			"max": [3],
			"scale": [1],
			"offset": [0]
		},{
			"name": "time",
			"description": "",
			"size": 4,
			"numElements": 1,
			"elementSize": 4,
			"type": "int32",
			"min": [404268097],
			"max": [605749695],
			"scale": [9.9999999999999995e-07],
			"offset": [0]
		}
	]
}
